LICENSE
README.md
pyproject.toml
src/eipi/__init__.py
src/eipi/cli.py
src/eipi/config.py
src/eipi/constants.py
src/eipi/errors.py
src/eipi/module.py
src/eipi/parser.py
src/eipi/register_module.py
src/eipi.egg-info/PKG-INFO
src/eipi.egg-info/SOURCES.txt
src/eipi.egg-info/dependency_links.txt
src/eipi.egg-info/entry_points.txt
src/eipi.egg-info/requires.txt
src/eipi.egg-info/top_level.txt
src/eipi/helper_functions/__init__.py
src/eipi/helper_functions/payload_request.py
src/eipi/helper_functions/request_data.py
src/eipi/helpers/__init__.py
src/eipi/helpers/module_database_helper.py
src/eipi/modules/__init__.py
src/eipi/modules/database.py
src/eipi/modules/eipi_env.py
src/eipi/templates/root_file.py
src/eipi/templates/yaml_file.py
src/eipi/validators/headers.py
src/eipi/validators/requests.py
src/eipi/validators/validate_inputs.py