Metadata-Version: 2.1
Name: eipi
Version: 0.0.2
Summary: Eipi is a declarative language for building modular APIs effortlessly. With Eipi, APIs are defined through simple configurations, focusing more on intent than implementation. Think of it as a framework that feels like a language expressive, lightweight, and scalable.
Author-email: Eric Kweyunga <maverickweyunga@gmail.com>
Project-URL: Homepage, https://github.com/am-eric-kweyunga/eipi
Project-URL: Issues, https://github.com/am-eric-kweyunga/eipi/issues
Classifier: Programming Language :: Python :: 3
Classifier: License :: OSI Approved :: MIT License
Classifier: Operating System :: OS Independent
Requires-Python: >=3.8
License-File: LICENSE
Requires-Dist: click
Requires-Dist: flask
Requires-Dist: pyyaml
Requires-Dist: tinydb
Requires-Dist: flask_cors
Requires-Dist: python-dotenv
Requires-Dist: requests
